LICENSE
MANIFEST.in
README.md
pysolrtornado.py
setup.cfg
setup.py
pysolr_tornado.egg-info/PKG-INFO
pysolr_tornado.egg-info/SOURCES.txt
pysolr_tornado.egg-info/dependency_links.txt
pysolr_tornado.egg-info/requires.txt
pysolr_tornado.egg-info/top_level.txt