Metadata-Version: 1.1
Name: pysolr-tornado
Version: 3.3.4
Summary: A library to access Solr via Tornado coroutines.
Home-page: https://github.com/CANTUS-Project/pysolr-tornado/
Author: Daniel Lindsley, Joseph Kocherhans, Jacob Kaplan-Moss, Christopher Antila
Author-email: christopher@antila.ca
License: BSD
Platform: UNKNOWN
Classifier: Development Status :: 5 - Production/Stable
Classifier: Intended Audience :: Developers
Classifier: License :: OSI Approved :: BSD License
Classifier: Operating System :: OS Independent
Classifier: Programming Language :: Python
Classifier: Topic :: Internet :: WWW/HTTP :: Indexing/Search
Classifier: Programming Language :: Python :: 3.3
Classifier: Programming Language :: Python :: 3.4
Classifier: Programming Language :: Python :: 3.5
Classifier: Programming Language :: Python :: Implementation :: CPython
